package simpleJVM;

/**
 * Created by qc1iu on 4/2/16.
 */
class ByteCode
{
  static final int OPC_NOP = 0;
  static final int OPC_ACONST_NULL = 1;
  static final int OPC_ICONST_M1 = 2;
  static final int OPC_ICONST_0 = 3;
  static final int OPC_ICONST_1 = 4;
  static final int OPC_ICONST_2 = 5;
  static final int OPC_ICONST_3 = 6;
  static final int OPC_ICONST_4 = 7;
  static final int OPC_ICONST_5 = 8;
  static final int OPC_LCONST_0 = 9;
  static final int OPC_LCONST_1 = 10;
  static final int OPC_FCONST_0 = 11;
  static final int OPC_FCONST_1 = 12;
  static final int OPC_FCONST_2 = 13;
  static final int OPC_DCONST_0 = 14;
  static final int OPC_DCONST_1 = 15;
  static final int OPC_BIPUSH = 16;
  static final int OPC_SIPUSH = 17;
  static final int OPC_LDC = 18;
  static final int OPC_LDC_W = 19;
  static final int OPC_LDC2_W = 20;
  static final int OPC_ILOAD = 21;
  static final int OPC_LLOAD = 22;
  static final int OPC_FLOAD = 23;
  static final int OPC_DLOAD = 24;
  static final int OPC_ALOAD = 25;
  static final int OPC_ILOAD_0 = 26;
  static final int OPC_ILOAD_1 = 27;
  static final int OPC_ILOAD_2 = 28;
  static final int OPC_ILOAD_3 = 29;
  static final int OPC_LLOAD_0 = 30;
  static final int OPC_LLOAD_1 = 31;
  static final int OPC_LLOAD_2 = 32;
  static final int OPC_LLOAD_3 = 33;
  static final int OPC_FLOAD_0 = 34;
  static final int OPC_FLOAD_1 = 35;
  static final int OPC_FLOAD_2 = 36;
  static final int OPC_FLOAD_3 = 37;
  static final int OPC_DLOAD_0 = 38;
  static final int OPC_DLOAD_1 = 39;
  static final int OPC_DLOAD_2 = 40;
  static final int OPC_DLOAD_3 = 41;
  static final int OPC_ALOAD_0 = 42;
  static final int OPC_ALOAD_1 = 43;
  static final int OPC_ALOAD_2 = 44;
  static final int OPC_ALOAD_3 = 45;
  static final int OPC_IALOAD = 46;
  static final int OPC_LALOAD = 47;
  static final int OPC_FALOAD = 48;
  static final int OPC_DALOAD = 49;
  static final int OPC_AALOAD = 50;
  static final int OPC_BALOAD = 51;
  static final int OPC_CALOAD = 52;
  static final int OPC_SALOAD = 53;
  static final int OPC_ISTORE = 54;
  static final int OPC_LSTORE = 55;
  static final int OPC_FSTORE = 56;
  static final int OPC_DSTORE = 57;
  static final int OPC_ASTORE = 58;
  static final int OPC_ISTORE_0 = 59;
  static final int OPC_ISTORE_1 = 60;
  static final int OPC_ISTORE_2 = 61;
  static final int OPC_ISTORE_3 = 62;
  static final int OPC_LSTORE_0 = 63;
  static final int OPC_LSTORE_1 = 64;
  static final int OPC_LSTORE_2 = 65;
  static final int OPC_LSTORE_3 = 66;
  static final int OPC_FSTORE_0 = 67;
  static final int OPC_FSTORE_1 = 68;
  static final int OPC_FSTORE_2 = 69;
  static final int OPC_FSTORE_3 = 70;
  static final int OPC_DSTORE_0 = 71;
  static final int OPC_DSTORE_1 = 72;
  static final int OPC_DSTORE_2 = 73;
  static final int OPC_DSTORE_3 = 74;
  static final int OPC_ASTORE_0 = 75;
  static final int OPC_ASTORE_1 = 76;
  static final int OPC_ASTORE_2 = 77;
  static final int OPC_ASTORE_3 = 78;
  static final int OPC_IASTORE = 79;
  static final int OPC_LASTORE = 80;
  static final int OPC_FASTORE = 81;
  static final int OPC_DASTORE = 82;
  static final int OPC_AASTORE = 83;
  static final int OPC_BASTORE = 84;
  static final int OPC_CASTORE = 85;
  static final int OPC_SASTORE = 86;
  static final int OPC_POP = 87;
  static final int OPC_POP2 = 88;
  static final int OPC_DUP = 89;
  static final int OPC_DUP_X1 = 90;
  static final int OPC_DUP_X2 = 91;
  static final int OPC_DUP2 = 92;
  static final int OPC_DUP2_X1 = 93;
  static final int OPC_DUP2_X2 = 94;
  static final int OPC_SWAP = 95;
  static final int OPC_IADD = 96;
  static final int OPC_LADD = 97;
  static final int OPC_FADD = 98;
  static final int OPC_DADD = 99;
  static final int OPC_ISUB = 100;
  static final int OPC_LSUB = 101;
  static final int OPC_FSUB = 102;
  static final int OPC_DSUB = 103;
  static final int OPC_IMUL = 104;
  static final int OPC_LMUL = 105;
  static final int OPC_FMUL = 106;
  static final int OPC_DMUL = 107;
  static final int OPC_IDIV = 108;
  static final int OPC_LDIV = 109;
  static final int OPC_FDIV = 110;
  static final int OPC_DDIV = 111;
  static final int OPC_IREM = 112;
  static final int OPC_LREM = 113;
  static final int OPC_FREM = 114;
  static final int OPC_DREM = 115;
  static final int OPC_INEG = 116;
  static final int OPC_LNEG = 117;
  static final int OPC_FNEG = 118;
  static final int OPC_DNEG = 119;
  static final int OPC_ISHL = 120;
  static final int OPC_LSHL = 121;
  static final int OPC_ISHR = 122;
  static final int OPC_LSHR = 123;
  static final int OPC_IUSHR = 124;
  static final int OPC_LUSHR = 125;
  static final int OPC_IAND = 126;
  static final int OPC_LAND = 127;
  static final int OPC_IOR = 128;
  static final int OPC_LOR = 129;
  static final int OPC_IXOR = 130;
  static final int OPC_LXOR = 131;
  static final int OPC_IINC = 132;
  static final int OPC_I2L = 133;
  static final int OPC_I2F = 134;
  static final int OPC_I2D = 135;
  static final int OPC_L2I = 136;
  static final int OPC_L2F = 137;
  static final int OPC_L2D = 138;
  static final int OPC_F2I = 139;
  static final int OPC_F2L = 140;
  static final int OPC_F2D = 141;
  static final int OPC_D2I = 142;
  static final int OPC_D2L = 143;
  static final int OPC_D2F = 144;
  static final int OPC_I2B = 145;
  static final int OPC_I2C = 146;
  static final int OPC_I2S = 147;
  static final int OPC_LCMP = 148;
  static final int OPC_FCMPL = 149;
  static final int OPC_FCMPG = 150;
  static final int OPC_DCMPL = 151;
  static final int OPC_DCMPG = 152;
  static final int OPC_IFEQ = 153;
  static final int OPC_IFNE = 154;
  static final int OPC_IFLT = 155;
  static final int OPC_IFGE = 156;
  static final int OPC_IFGT = 157;
  static final int OPC_IFLE = 158;
  static final int OPC_IF_ICMPEQ = 159;
  static final int OPC_IF_ICMPNE = 160;
  static final int OPC_IF_ICMPLT = 161;
  static final int OPC_IF_ICMPGE = 162;
  static final int OPC_IF_ICMPGT = 163;
  static final int OPC_IF_ICMPLE = 164;
  static final int OPC_IF_ACMPEQ = 165;
  static final int OPC_IF_ACMPNE = 166;
  static final int OPC_GOTO = 167;
  static final int OPC_JSR = 168;
  static final int OPC_RET = 169;
  static final int OPC_TABLESWITCH = 170;
  static final int OPC_LOOKUPSWITCH = 171;
  static final int OPC_IRETURN = 172;
  static final int OPC_LRETURN = 173;
  static final int OPC_FRETURN = 174;
  static final int OPC_DRETURN = 175;
  static final int OPC_ARETURN = 176;
  static final int OPC_RETURN = 177;
  static final int OPC_GETSTATIC = 178;
  static final int OPC_PUTSTATIC = 189;
  static final int OPC_GETFIELD = 180;
  static final int OPC_PUTFIELD = 181;
  static final int OPC_INVOKEVIRTUAL = 182;
  static final int OPC_INVOKESPECIAL = 183;
  static final int OPC_INVOKESTATIC = 184;
  static final int OPC_INVOKEINTERFACE = 185;
  static final int OPC_INVOKEDYYNAMIC = 186;
  static final int OPC_NEW = 187;
  static final int OPC_NEWARRAY = 188;
  static final int OPC_ANEWARRAY = 189;
  static final int OPC_ARRAYLENGTH = 190;
  static final int OPC_ATHROW = 191;
  static final int OPC_CHECKCAST = 192;
  static final int OPC_INSTANCEOF = 193;
  static final int OPC_MONITORENTER = 194;
  static final int OPC_MONITOREXIT = 195;
  static final int OPC_WIDE = 196;
  static final int OPC_MULTIANEWARRAY = 197;
  static final int OPC_IFNULL = 198;
  static final int OPC_IFNONNULL = 199;
  static final int OPC_GOTO_W = 200;
  static final int OPC_JSR_W = 201;
}
